zhmiscellany_ocr/__init__.py
zhmiscellany_ocr/_ocr_supportfuncs.py
zhmiscellany_ocr/_py_resources.py
zhmiscellany_ocr-0.0.8.dist-info/METADATA
zhmiscellany_ocr-0.0.8.dist-info/WHEEL
zhmiscellany_ocr-0.0.8.dist-info/top_level.txt
zhmiscellany_ocr-0.0.8.dist-info/RECORD
